bladebit_harvester.dll
chikpos.cp312-win_amd64.pyd
chikpos-2.0.11.dist-info/licenses/LICENSE
chikpos-2.0.11.dist-info/METADATA
chikpos-2.0.11.dist-info/WHEEL
chikpos-2.0.11.dist-info/top_level.txt
chikpos-2.0.11.dist-info/RECORD
