Metadata-Version: 2.4
Name: chikpos
Version: 2.0.11
Summary: Chik proof of space plotting, proving, and verifying (wraps C++)
Home-page: https://github.com/Chik-Network/chikpos
Author: Mariano Sorgente
Author-email: mariano@chiknetwork.com
License: Apache-2.0
Requires-Python: >=3.7
License-File: LICENSE
Dynamic: author
Dynamic: author-email
Dynamic: description
Dynamic: description-content-type
Dynamic: home-page
Dynamic: license
Dynamic: license-file
Dynamic: requires-python
Dynamic: summary
